Lab2/Lab2_encoder_5bit_behavior.v
module	Lab2_encoder_5bit_behavior(
	input [0:4]D, 
	output reg [2:0]A,
	output reg V);
	///*
	always@(*)
		begin
			V = !(D == 5'b00000);
			A[2] = D == 5'b00001;
			A[1] = (~D[0] & ~D[1] & D[2]) | (~D[0] & ~D[1] & D[3]);
			A[0] = (~D[0] & D[1]) | (~D[0] & ~D[2] & D[3]);
		end
	//*/
	/*
	always@(D, A, V)
		if(D[0])	  {A,V} = 4'b0001;
		else if(D[1]) {A,V} = 4'b0011;
		else if(D[2]) {A,V} = 4'b0101;
		else if(D[3]) {A,V} = 4'b0111;
		else if(D[4]) {A,V} = 4'b1001;
		else		  V = 1'b0;
	*/
endmodule

Lab2/Lab2_encoder_5bit_dataflow.v
module	Lab2_encoder_5bit_dataflow(
	input [0:4]D, 
	output [2:0]A,
	output V);
	
	assign	V = !(D == 5'b00000);
	assign	A[2] = D == 5'b00001;
	assign	A[1] = (~D[0] & ~D[1] & D[2]) | (~D[0] & ~D[1] & D[3]);
	assign	A[0] = (~D[0] & D[1]) | (~D[0] & ~D[2] & D[3]);
endmodule

Lab2/Lab2_encoder_5bit_gate_level.v
module	Lab2_encoder_5bit_gate_level(
	input [0:4]D, 
	output [2:0]A,
	output V);
	wire	[0:4]_D;
	wire	A1_1, A1_2, A0_1, A0_2;
	
	or	G1(V, D[0], D[1], D[2], D[3], D[4]);
	not	(_D[0], D[0]),
		(_D[1], D[1]),
		(_D[2], D[2]),
		(_D[3], D[3]),
		(_D[4], D[4]);
		
	and	G2(A[2], _D[0], _D[1], _D[2], _D[3], D[4]);
	
	and	G3(A1_1, _D[0], _D[1], D[2]),
		G4(A1_2, _D[0], _D[1], D[3]);
	or	G5(A[1], A1_1, A1_2);
	
	and	G6(A0_1, _D[0], D[1]),
		G7(A0_2, _D[0], _D[2], D[3]);
	or	G8(A[0], A0_1, A0_2);
endmodule

Lab2/t_Lab2_encoder_5bit.v
module	t_Lab2_encoder_5bit;
	reg [0:4]D;
	wire [2:0]A_gatelevel, A_dataflow, A_behavior;
	wire V_gatelevel, V_dataflow, V_behavior;
	parameter stop_time = 400;
	//instantiate device under test
	Lab2_encoder_5bit_gate_level	M1(D, A_gatelevel, V_gatelevel);
	Lab2_encoder_5bit_dataflow		M2(D, A_dataflow, V_dataflow);
	Lab2_encoder_5bit_behavior		M3(D, A_behavior, V_behavior);
	initial #stop_time $finish;
	//apply inputs one at a time
	initial	begin
		D = 5'b00000;
		#50 D = 5'b00001;
		#50 D = 5'b00011;
		#50 D = 5'b00110;
		#50 D = 5'b01001;
		#50 D = 5'b01101;
		#50 D = 5'b10110;
		#50 D = 5'b11010;
	end

	//dump the result of simulation
	initial begin
		$dumpfile("t_Lab2_encoder_5bit.vcd");
		$dumpvars;
	end
endmodule

Lab2/t_Lab2_encoder_5bit.vcd
$date
	Sun May 09 16:37:09 2021
$end
$version
	Icarus Verilog
$end
$timescale
	1s
$end
$scope module t_Lab2_encoder_5bit $end
$var wire 1 ! V_gatelevel $end
$var wire 1 " V_dataflow $end
$var wire 1 # V_behavior $end
$var wire 3 $ A_gatelevel [2:0] $end
$var wire 3 % A_dataflow [2:0] $end
$var wire 3 & A_behavior [2:0] $end
$var reg 5 ' D [0:4] $end
$scope module M1 $end
$var wire 1 ( A0_1 $end
$var wire 1 ) A0_2 $end
$var wire 1 * A1_1 $end
$var wire 1 + A1_2 $end
$var wire 5 , D [0:4] $end
$var wire 1 ! V $end
$var wire 5 - _D [0:4] $end
$var wire 3 . A [2:0] $end
$upscope $end
$scope module M2 $end
$var wire 5 / D [0:4] $end
$var wire 1 " V $end
$var wire 3 0 A [2:0] $end
$upscope $end
$scope module M3 $end
$var wire 5 1 D [0:4] $end
$var reg 3 2 A [2:0] $end
$var reg 1 # V $end
$upscope $end
$upscope $end
$enddefinitions $end
#0
$dumpvars
b0 2
b0 1
b0 0
b0 /
b0 .
b11111 -
b0 ,
0+
0*
0)
0(
b0 '
b0 &
b0 %
b0 $
0#
0"
0!
$end
#50
1!
b100 $
b100 .
b11110 -
b100 &
b100 2
1#
1"
b100 %
b100 0
b1 '
b1 ,
b1 /
b1 1
#100
b11 $
b11 .
b11100 -
1+
1)
b11 &
b11 2
b11 %
b11 0
b11 '
b11 ,
b11 /
b11 1
#150
b10 $
b10 .
b10 %
b10 0
0)
b11001 -
1*
b10 &
b10 2
b110 '
b110 ,
b110 /
b110 1
#200
b1 $
b1 .
b1 %
b1 0
b10110 -
0*
0+
1(
b1 &
b1 2
b1001 '
b1001 ,
b1001 /
b1001 1
#250
b10010 -
b1101 '
b1101 ,
b1101 /
b1101 1
#300
b0 $
b0 .
b0 %
b0 0
b1001 -
0(
b0 &
b0 2
b10110 '
b10110 ,
b10110 /
b10110 1
#350
b101 -
b11010 '
b11010 ,
b11010 /
b11010 1
