Lab2/Lab2_half_sub_gatelevel.v
module	Lab2_half_sub_gatelevel(
	input x, y, 
	output B, D);
	wire	_x;
	
	not	(_x, x);
	
	and	#(2)G1(B, _x, y);
	xor #(4)G2(D, x, y);
endmodule

Lab2/t_Lab2_half_sub.v
module	t_Lab2_half_sub;
	wire	B, D;
	reg		x, y;
	parameter stop_time = 50;
	//instantiate device under test
	Lab2_half_sub_gatelevel M1(x, y, B, D);
	
	initial #stop_time $finish;
	//apply inputs one at a time
	initial	begin
		{x,y} = 2'b00;
		repeat(3) #10 {x,y} = {x,y} + 1'b1;
	end

	//dump the result of simulation
	initial begin
		$dumpfile("t_Lab2_half_sub.vcd");
		$dumpvars;
	end
endmodule

Lab2/t_Lab2_half_sub.vcd
$date
	Sun May 09 16:36:21 2021
$end
$version
	Icarus Verilog
$end
$timescale
	1s
$end
$scope module t_Lab2_half_sub $end
$var wire 1 ! D $end
$var wire 1 " B $end
$var reg 1 # x $end
$var reg 1 $ y $end
$scope module M1 $end
$var wire 1 " B $end
$var wire 1 ! D $end
$var wire 1 % _x $end
$var wire 1 # x $end
$var wire 1 $ y $end
$upscope $end
$upscope $end
$enddefinitions $end
#0
$dumpvars
1%
0$
0#
x"
x!
$end
#2
0"
#4
0!
#10
1$
#12
1"
#14
1!
#20
0%
1#
0$
#22
0"
#30
1$
#34
0!
