Lab2/Lab2_half_sub_gatelevel.v
module	Lab2_half_sub_gatelevel(
	input x, y, 
	output B, D);
	wire	_x;
	
	not	(_x, x);
	
	and	#(2)G1(B, _x, y);
	xor #(4)G2(D, x, y);
endmodule

Lab2/Lab2_full_sub.v
module	Lab2_full_sub(
	input x, y, z, 
	output B, D);
	wire	w1, B1, B2;
	
	Lab2_half_sub_gatelevel M1(x, y, B1, w1);
	Lab2_half_sub_gatelevel M2(w1, z, B2, D);
	or	#(2)G1(B, B1, B2);
	
endmodule

Lab2/t_Lab2_full_sub.v
module	t_Lab2_full_sub;
	wire	B, D;
	reg		x, y, z;
	parameter stop_time = 400;
	//instantiate device under test
	Lab2_full_sub M1(x, y, z, B, D);
	
	initial #stop_time $finish;
	//apply inputs one at a time
	initial	begin
		{x,y,z} = 3'b000;
		repeat(7) #50 {x,y,z} = {x,y,z} + 1'b1;
	end

	//dump the result of simulation
	initial begin
		$dumpfile("t_Lab2_full_sub.vcd");
		$dumpvars;
	end
endmodule

Lab2/t_Lab2_full_sub.vcd
$date
	Sun May 09 16:35:48 2021
$end
$version
	Icarus Verilog
$end
$timescale
	1s
$end
$scope module t_Lab2_full_sub $end
$var wire 1 ! D $end
$var wire 1 " B $end
$var reg 1 # x $end
$var reg 1 $ y $end
$var reg 1 % z $end
$scope module M1 $end
$var wire 1 " B $end
$var wire 1 # x $end
$var wire 1 $ y $end
$var wire 1 % z $end
$var wire 1 & w1 $end
$var wire 1 ! D $end
$var wire 1 ' B2 $end
$var wire 1 ( B1 $end
$scope module M1 $end
$var wire 1 ( B $end
$var wire 1 & D $end
$var wire 1 ) _x $end
$var wire 1 # x $end
$var wire 1 $ y $end
$upscope $end
$scope module M2 $end
$var wire 1 ' B $end
$var wire 1 ! D $end
$var wire 1 * _x $end
$var wire 1 & x $end
$var wire 1 % y $end
$upscope $end
$upscope $end
$upscope $end
$enddefinitions $end
#0
$dumpvars
x*
1)
x(
x'
x&
0%
0$
0#
x"
x!
$end
#2
0'
0(
#4
1*
0"
0&
#8
0!
#50
1%
#52
1'
#54
1"
1!
#100
1$
0%
#102
1(
0'
#104
0*
1&
0!
#108
1!
#150
1%
#154
0!
#200
0)
1#
0$
0%
#202
0(
#204
0"
1!
#250
1%
#254
0!
#300
1$
0%
#304
1*
0&
1!
#308
0!
#350
1%
#352
1'
#354
1"
1!
