Lab3/Lab3_SbRb_Latch_gatelevel.v
module	Lab3_SbRb_Latch_gatelevel(
	input Sb, Rb, 
	output Q, Qb);
	
	nand #(5) 	(Q, Sb, Qb),
				(Qb, Rb, Q);
				
endmodule

Lab3/t_Lab3_SbRb_Latch_gatelevel.v
module	t_Lab3_SbRb_Latch_gatelevel;
	wire	Q, Qb;
	reg 	Sb, Rb;
	parameter stop_time = 250;
	//instantiate device under test
	Lab3_SbRb_Latch_gatelevel M0(Sb, Rb, Q, Qb);
	
	initial #stop_time $finish;
	
	//
	initial	fork
		Sb = 0; Rb = 1;
		#30  Sb = 1; #30  Rb = 1;
		#60  Sb = 1; #60  Rb = 0;
		#90  Sb = 1; #90  Rb = 1;
		#120 Sb = 0; #120 Rb = 0;
		#150 Sb = 1; #150 Rb = 1;
		#180 Sb = 0; #180 Rb = 1;
	join

	//dump the result of simulation
	initial begin
		$dumpfile("t_Lab3_SbRb_Latch_gatelevel.vcd");
		$dumpvars;
	end
endmodule

Lab3/t_Lab3_SbRb_Latch_gatelevel.vcd
$date
	Mon May 31 10:23:13 2021
$end
$version
	Icarus Verilog
$end
$timescale
	1s
$end
$scope module t_Lab3_SbRb_Latch_gatelevel $end
$var wire 1 ! Qb $end
$var wire 1 " Q $end
$var reg 1 # Rb $end
$var reg 1 $ Sb $end
$scope module M0 $end
$var wire 1 " Q $end
$var wire 1 ! Qb $end
$var wire 1 # Rb $end
$var wire 1 $ Sb $end
$upscope $end
$upscope $end
$enddefinitions $end
#0
$dumpvars
0$
1#
x"
x!
$end
#5
1"
#10
0!
#30
1$
#60
0#
#65
1!
#70
0"
#90
1#
#120
0$
0#
#125
1"
#150
1$
1#
#155
0"
0!
#160
1!
1"
#165
0"
0!
#170
1!
1"
#175
0"
0!
#180
1!
1"
0$
#185
0!
