Lab3/D_ff_AR.v
module	D_ff_AR(
	input D, clock, reset, 
	output reg Q);
	
	always @ (posedge clock, negedge reset)
		if (reset == 0) Q <= 1'b0; 
		else Q <= D;
	
endmodule

Lab3/Lab3_Sequence_Recognizer_structure.v
module	Lab3_Sequence_Recognizer_structure (
	input x, clock, reset, 
	output z);
	
	wire A, B, C, DA, DB, DC;
	wire [2:0]state_structure;
	// Flip-flop input equations
	assign DA = (~C & x) | (C & B & ~x);
	assign DB = (C & x) | (~C & ~x & B) | (~C & ~x & A);
	assign DC = ~x;
	//output equation
	assign z = (~C & ~x & B) | (C & x & A);
	//Instantiate D flip-flops
	D_ff_AR DffA(DA, clock, reset, A);
	D_ff_AR DffB(DB, clock, reset, B);
	D_ff_AR DffC(DC, clock, reset, C);
	//for test
	assign state_structure = {A,B,C};
	
endmodule

Lab3/Lab3_Sequence_Recognizer_state_diagram.v
module	Lab3_Sequence_Recognizer_state_diagram (
	input x, clock, reset,
	output reg z);
	
	reg [2:0]state, next_state;
	//state list
	parameter 	S0 = 3'b000, 
				S1 = 3'b001, 
				S2 = 3'b010, 
				S3 = 3'b011, 
				S4 = 3'b100, 
				S5 = 3'b101;
	//state register
	always@(posedge clock, negedge reset)
		if(reset == 0) state <= S0;
		else state <= next_state;
	//next state combinational logic
	always@(state, x)
		 case(state)
			S0: if (x) next_state = S4; else next_state = S1;
			S1: if (x) next_state = S2; else next_state = S1;
			S2: if (x) next_state = S4; else next_state = S3;
			S3: if (x) next_state = S2; else next_state = S5;
			S4: if (x) next_state = S4; else next_state = S3;
			S5: if (x) next_state = S2; else next_state = S1;
		endcase
	//output combinational logic
	always@(state, x)
		case (state)
			S2: z = ~x;
			S5: z = x;
			default: z = 0;
		endcase
		
endmodule

Lab3/t_Lab3_Sequence_Recognizer.v
module	t_Lab3_Sequence_Recognizer;
	wire	z_state_diagram, z_structure;
	reg 	x, clock, reset;
	parameter stop_time = 150;
	//instantiate device under test
	Lab3_Sequence_Recognizer_state_diagram 	state_diagram	(x, clock, reset, z_state_diagram);
	Lab3_Sequence_Recognizer_structure 		structure		(x, clock, reset, z_structure);
	//
	initial #stop_time $finish;
	//
	initial begin 
		reset = 0;
		clock = 0; 
		forever #5 clock = ~clock; 
	end
	//
	initial	fork
		x = 1;
		#4 reset = 1;
		#10 x = 1;
		#20 x = 0;
		#30 x = 0;
		#40 x = 1;
		#50 x = 0;
		#60 x = 1;
		#70 x = 1;
		#80 reset = 0;
		#80 x = 0;
		#84 reset = 1;
		#90 x = 0;
		#100 x = 1;
		#110 x = 0;
		#120 x = 0;
		#130 x = 0;
	join

	//dump the result of simulation
	initial begin
		$dumpfile("t_Lab3_Sequence_Recognizer.vcd");
		$dumpvars;
	end
endmodule

Lab3/t_Lab3_Sequence_Recognizer.vcd
$date
	Wed Jun 02 15:13:08 2021
$end
$version
	Icarus Verilog
$end
$timescale
	1s
$end
$scope module t_Lab3_Sequence_Recognizer $end
$var wire 1 ! z_structure $end
$var wire 1 " z_state_diagram $end
$var reg 1 # clock $end
$var reg 1 $ reset $end
$var reg 1 % x $end
$scope module state_diagram $end
$var wire 1 # clock $end
$var wire 1 $ reset $end
$var wire 1 % x $end
$var reg 3 & next_state [2:0] $end
$var reg 3 ' state [2:0] $end
$var reg 1 " z $end
$upscope $end
$scope module structure $end
$var wire 1 ( DA $end
$var wire 1 ) DB $end
$var wire 1 * DC $end
$var wire 1 # clock $end
$var wire 1 $ reset $end
$var wire 1 % x $end
$var wire 1 ! z $end
$var wire 3 + state_structure [2:0] $end
$var wire 1 , C $end
$var wire 1 - B $end
$var wire 1 . A $end
$scope module DffA $end
$var wire 1 ( D $end
$var wire 1 # clock $end
$var wire 1 $ reset $end
$var reg 1 . Q $end
$upscope $end
$scope module DffB $end
$var wire 1 ) D $end
$var wire 1 # clock $end
$var wire 1 $ reset $end
$var reg 1 - Q $end
$upscope $end
$scope module DffC $end
$var wire 1 * D $end
$var wire 1 # clock $end
$var wire 1 $ reset $end
$var reg 1 , Q $end
$upscope $end
$upscope $end
$upscope $end
$enddefinitions $end
#0
$dumpvars
0.
0-
0,
b0 +
0*
0)
1(
b0 '
b100 &
1%
0$
0#
0"
0!
$end
#4
1$
#5
b100 +
1.
b100 '
1#
#10
0#
#15
1#
#20
1)
0(
b11 &
1*
0#
0%
#25
1(
0!
0)
b101 &
1,
1-
b11 +
0.
b11 '
1#
#30
0#
#35
0(
b1 &
b101 '
1.
b101 +
0-
1#
#40
1)
1!
1"
b10 &
0*
0#
1%
#45
0)
1(
0!
b100 &
0"
0,
1-
b10 +
0.
b10 '
1#
#50
1)
1!
0(
1"
b11 &
1*
0#
0%
#55
0)
0!
1(
b101 &
0"
b11 '
b11 +
1,
1#
#60
0(
1)
b10 &
0*
0#
1%
#65
0)
1(
b100 &
b10 +
0,
b10 '
1#
#70
0#
#75
b100 '
1.
b100 +
0-
1#
#80
b0 +
0.
b0 '
0)
0(
b1 &
1*
0#
0$
0%
#84
1$
#85
b1 '
b1 +
1,
1#
#90
0#
#95
1#
#100
1)
b10 &
0*
0#
1%
#105
0)
1(
b100 &
b10 '
1-
b10 +
0,
1#
#110
1)
1!
0(
1"
b11 &
1*
0#
0%
#115
0)
0!
1(
b101 &
0"
b11 +
1,
b11 '
1#
#120
0#
#125
0(
b1 &
b101 '
1.
b101 +
0-
1#
#130
0#
#135
b1 +
0.
b1 '
1#
